htbst/__init__.py
htbst/const.py
htbst/htb.py
htbst/labs.py
htbst-0.3.dist-info/METADATA
htbst-0.3.dist-info/WHEEL
htbst-0.3.dist-info/entry_points.txt
htbst-0.3.dist-info/top_level.txt
htbst-0.3.dist-info/RECORD
