Metadata-Version: 2.1
Name: htbst
Version: 0.3
Author: replican
Classifier: Development Status :: 3 - Alpha
Classifier: Programming Language :: Python :: 3
Classifier: License :: OSI Approved :: MIT License
Requires-Dist: httpx
Requires-Dist: asyncio
